SimpleHTTP404Server.py
SimpleHTTP404Server-0.2.0.dist-info/DESCRIPTION.rst
SimpleHTTP404Server-0.2.0.dist-info/METADATA
SimpleHTTP404Server-0.2.0.dist-info/metadata.json
SimpleHTTP404Server-0.2.0.dist-info/RECORD
SimpleHTTP404Server-0.2.0.dist-info/top_level.txt
SimpleHTTP404Server-0.2.0.dist-info/WHEEL
