Metadata-Version: 2.0
Name: SimpleHTTP404Server
Version: 0.2.0
Summary: A Python SimpleHTTPServer, but serves 404.html if a page is not found.
Home-page: http://github.com/clokep/SimpleHTTP404Server/
Author: Patrick Cloke
Author-email: patrick@cloke.us
License: MIT
Platform: UNKNOWN
Classifier: Development Status :: 5 - Production/Stable
Classifier: Intended Audience :: Developers
Classifier: Natural Language :: English
Classifier: License :: OSI Approved :: MIT License
Classifier: Operating System :: OS Independent
Classifier: Programming Language :: Python
Classifier: Programming Language :: Python :: 2
Classifier: Programming Language :: Python :: 2.7
Classifier: Programming Language :: Python :: 3.3
Classifier: Topic :: Internet :: WWW/HTTP
Classifier: Topic :: Software Development :: Libraries :: Python Modules
